templatequery/__init__.py
templatequery/template_query.py
templatequery-0.1.3.dist-info/LICENSE
templatequery-0.1.3.dist-info/METADATA
templatequery-0.1.3.dist-info/WHEEL
templatequery-0.1.3.dist-info/top_level.txt
templatequery-0.1.3.dist-info/RECORD
