Metadata-Version: 2.1
Name: templatequery
Version: 0.1.3
Summary: Convenient formatting for psycopg2 SQL queries
Home-page: https://github.com/pjdon/templatequery
Author: Paul Donchenko
Author-email: pjdonch@gmail.com
License: UNKNOWN
Platform: UNKNOWN
Classifier: Programming Language :: Python :: 3
Classifier: License :: OSI Approved :: GNU Lesser General Public License v3 (LGPLv3)
Classifier: Operating System :: OS Independent
Requires-Python: >=3.6
Requires-Dist: psycopg2 (>=2.7.5)
